selenide/__init__.py
selenide/browser.py
selenide/configuration.py
selenide/entity.py
selenide/handler.py
selenide/page.py
selenide/selectors.py
selenide-0.0.15.dist-info/LICENSE
selenide-0.0.15.dist-info/METADATA
selenide-0.0.15.dist-info/WHEEL
selenide-0.0.15.dist-info/top_level.txt
selenide-0.0.15.dist-info/RECORD
