Metadata-Version: 2.1
Name: selenide
Version: 0.0.15
Summary: Automation powered by Selenium WebDriver.
Home-page: https://github.com/aquichita/selenide
Author: aquichita
Author-email: chaochao.wu@outlook.com
License: MIT
Download-URL: https://github.com/aquichita/selenide/tarball/0.0.15
Requires-Dist: allure-pytest (==2.8.19)
Requires-Dist: PyMySQL (==0.10.1)
Requires-Dist: pytest (==6.1.2)
Requires-Dist: PyYAML (==5.3.1)
Requires-Dist: selenium (==3.141.0)
